{
  "a_comp_cor_00": {
    "CumulativeVarianceExplained": 0.0908164511,
    "Mask": "combined",
    "Method": "aCompCor",
    "Retained": true,
    "SingularValue": 242.6442136824,
    "VarianceExplained": 0.0908164511
  },
  "a_comp_cor_01": {
    "CumulativeVarianceExplained": 0.1328605777,
    "Mask": "combined",
    "Method": "aCompCor",
    "Retained": true,
    "SingularValue": 165.0974416867,
    "VarianceExplained": 0.0420441266
  },
  "a_comp_cor_02": {
    "CumulativeVarianceExplained": 0.1674725842,
    "Mask": "combined",
    "Method": "aCompCor",
    "Retained": true,
    "SingularValue": 149.7962923604,
    "VarianceExplained": 0.0346120065
  },
  "a_comp_cor_03": {
    "CumulativeVarianceExplained": 0.2017269054,
    "Mask": "combined",
    "Method": "aCompCor",
    "Retained": true,
    "SingularValue": 149.0202742233,
    "VarianceExplained": 0.0342543211
  },
  "a_comp_cor_04": {
    "CumulativeVarianceExplained": 0.2332182634,
    "Mask": "combined",
    "Method": "aCompCor",
    "Retained": true,
    "SingularValue": 142.8839247394,
    "VarianceExplained": 0.0314913581
  },
  "a_comp_cor_05": {
    "CumulativeVarianceExplained": 0.2563888042,
    "Mask": "combined",
    "Method": "aCompCor",
    "Retained": true,
    "SingularValue": 122.5619777108,
    "VarianceExplained": 0.0231705407
  },
  "a_comp_cor_06": {
    "CumulativeVarianceExplained": 0.276167287,
    "Mask": "combined",
    "Method": "aCompCor",
    "Retained": true,
    "SingularValue": 113.2359069404,
    "VarianceExplained": 0.0197784828
  },
  "a_comp_cor_07": {
    "CumulativeVarianceExplained": 0.2919918911,
    "Mask": "combined",
    "Method": "aCompCor",
    "Retained": true,
    "SingularValue": 101.2870922389,
    "VarianceExplained": 0.0158246042
  },
  "a_comp_cor_08": {
    "CumulativeVarianceExplained": 0.3059500374,
    "Mask": "combined",
    "Method": "aCompCor",
    "Retained": true,
    "SingularValue": 95.1265067739,
    "VarianceExplained": 0.0139581463
  },
  "a_comp_cor_09": {
    "CumulativeVarianceExplained": 0.3189743529,
    "Mask": "combined",
    "Method": "aCompCor",
    "Retained": true,
    "SingularValue": 91.8893395754,
    "VarianceExplained": 0.0130243155
  },
  "a_comp_cor_10": {
    "CumulativeVarianceExplained": 0.3314724646,
    "Mask": "combined",
    "Method": "aCompCor",
    "Retained": true,
    "SingularValue": 90.0139617813,
    "VarianceExplained": 0.0124981117
  },
  "a_comp_cor_11": {
    "CumulativeVarianceExplained": 0.3432242522,
    "Mask": "combined",
    "Method": "aCompCor",
    "Retained": true,
    "SingularValue": 87.2850049793,
    "VarianceExplained": 0.0117517875
  },
  "a_comp_cor_12": {
    "CumulativeVarianceExplained": 0.3541268892,
    "Mask": "combined",
    "Method": "aCompCor",
    "Retained": true,
    "SingularValue": 84.0724013935,
    "VarianceExplained": 0.010902637
  },
  "a_comp_cor_13": {
    "CumulativeVarianceExplained": 0.3639818492,
    "Mask": "combined",
    "Method": "aCompCor",
    "Retained": true,
    "SingularValue": 79.9309748253,
    "VarianceExplained": 0.00985496
  },
  "a_comp_cor_14": {
    "CumulativeVarianceExplained": 0.373196946,
    "Mask": "combined",
    "Method": "aCompCor",
    "Retained": true,
    "SingularValue": 77.2925483012,
    "VarianceExplained": 0.0092150968
  },
  "a_comp_cor_15": {
    "CumulativeVarianceExplained": 0.3818714506,
    "Mask": "combined",
    "Method": "aCompCor",
    "Retained": true,
    "SingularValue": 74.9911507621,
    "VarianceExplained": 0.0086745047
  },
  "a_comp_cor_16": {
    "CumulativeVarianceExplained": 0.3904100363,
    "Mask": "combined",
    "Method": "aCompCor",
    "Retained": true,
    "SingularValue": 74.4013208613,
    "VarianceExplained": 0.0085385857
  },
  "a_comp_cor_17": {
    "CumulativeVarianceExplained": 0.3987413087,
    "Mask": "combined",
    "Method": "aCompCor",
    "Retained": true,
    "SingularValue": 73.4925544286,
    "VarianceExplained": 0.0083312724
  },
  "a_comp_cor_18": {
    "CumulativeVarianceExplained": 0.4069621628,
    "Mask": "combined",
    "Method": "aCompCor",
    "Retained": true,
    "SingularValue": 73.0039141257,
    "VarianceExplained": 0.0082208541
  },
  "a_comp_cor_19": {
    "CumulativeVarianceExplained": 0.4146928424,
    "Mask": "combined",
    "Method": "aCompCor",
    "Retained": true,
    "SingularValue": 70.7940100649,
    "VarianceExplained": 0.0077306796
  },
  "a_comp_cor_20": {
    "CumulativeVarianceExplained": 0.4221624222,
    "Mask": "combined",
    "Method": "aCompCor",
    "Retained": true,
    "SingularValue": 69.5882253083,
    "VarianceExplained": 0.0074695798
  },
  "a_comp_cor_21": {
    "CumulativeVarianceExplained": 0.4295541913,
    "Mask": "combined",
    "Method": "aCompCor",
    "Retained": true,
    "SingularValue": 69.2248260628,
    "VarianceExplained": 0.0073917691
  },
  "a_comp_cor_22": {
    "CumulativeVarianceExplained": 0.4368168613,
    "Mask": "combined",
    "Method": "aCompCor",
    "Retained": true,
    "SingularValue": 68.617648608,
    "VarianceExplained": 0.00726267
  },
  "a_comp_cor_23": {
    "CumulativeVarianceExplained": 0.4440056808,
    "Mask": "combined",
    "Method": "aCompCor",
    "Retained": true,
    "SingularValue": 68.2678875785,
    "VarianceExplained": 0.0071888195
  },
  "a_comp_cor_24": {
    "CumulativeVarianceExplained": 0.4509575987,
    "Mask": "combined",
    "Method": "aCompCor",
    "Retained": true,
    "SingularValue": 67.1336087438,
    "VarianceExplained": 0.0069519179
  },
  "a_comp_cor_25": {
    "CumulativeVarianceExplained": 0.457855831,
    "Mask": "combined",
    "Method": "aCompCor",
    "Retained": true,
    "SingularValue": 66.8738896632,
    "VarianceExplained": 0.0068982323
  },
  "a_comp_cor_26": {
    "CumulativeVarianceExplained": 0.464709722,
    "Mask": "combined",
    "Method": "aCompCor",
    "Retained": true,
    "SingularValue": 66.6586129907,
    "VarianceExplained": 0.006853891
  },
  "a_comp_cor_27": {
    "CumulativeVarianceExplained": 0.4714513802,
    "Mask": "combined",
    "Method": "aCompCor",
    "Retained": true,
    "SingularValue": 66.1105911319,
    "VarianceExplained": 0.0067416582
  },
  "a_comp_cor_28": {
    "CumulativeVarianceExplained": 0.4780002549,
    "Mask": "combined",
    "Method": "aCompCor",
    "Retained": true,
    "SingularValue": 65.1584907385,
    "VarianceExplained": 0.0065488747
  },
  "a_comp_cor_29": {
    "CumulativeVarianceExplained": 0.4845030825,
    "Mask": "combined",
    "Method": "aCompCor",
    "Retained": true,
    "SingularValue": 64.9290122664,
    "VarianceExplained": 0.0065028276
  },
  "a_comp_cor_30": {
    "CumulativeVarianceExplained": 0.4909598069,
    "Mask": "combined",
    "Method": "aCompCor",
    "Retained": true,
    "SingularValue": 64.6984385553,
    "VarianceExplained": 0.0064567244
  },
  "a_comp_cor_31": {
    "CumulativeVarianceExplained": 0.4973905336,
    "Mask": "combined",
    "Method": "aCompCor",
    "Retained": true,
    "SingularValue": 64.568055011,
    "VarianceExplained": 0.0064307268
  },
  "a_comp_cor_32": {
    "CumulativeVarianceExplained": 0.5037736501,
    "Mask": "combined",
    "Method": "aCompCor",
    "Retained": true,
    "SingularValue": 64.3285940078,
    "VarianceExplained": 0.0063831164
  },
  "aroma_motion_1": {
    "CSFFraction": 0.02,
    "EdgeFraction": 0.68,
    "HighFrequencyContent": 0.05,
    "MaximumRpCorrelation": 0.96,
    "Method": {
      "Name": "ICA-AROMA",
      "Version": "0.4.5"
    },
    "ModelVarianceExplained": 0.1059442036,
    "MotionNoise": true,
    "TotalVarianceExplained": 0.1001719555
  },
  "aroma_motion_10": {
    "CSFFraction": 0.0,
    "EdgeFraction": 0.43,
    "HighFrequencyContent": 0.5,
    "MaximumRpCorrelation": 0.79,
    "Method": {
      "Name": "ICA-AROMA",
      "Version": "0.4.5"
    },
    "ModelVarianceExplained": 0.025511578,
    "MotionNoise": true,
    "TotalVarianceExplained": 0.024121609
  },
  "aroma_motion_11": {
    "CSFFraction": 0.02,
    "EdgeFraction": 0.88,
    "HighFrequencyContent": 0.65,
    "MaximumRpCorrelation": 0.64,
    "Method": {
      "Name": "ICA-AROMA",
      "Version": "0.4.5"
    },
    "ModelVarianceExplained": 0.025266463,
    "MotionNoise": true,
    "TotalVarianceExplained": 0.0238898488
  },
  "aroma_motion_12": {
    "CSFFraction": 0.03,
    "EdgeFraction": 0.32,
    "HighFrequencyContent": 0.59,
    "MaximumRpCorrelation": 0.84,
    "Method": {
      "Name": "ICA-AROMA",
      "Version": "0.4.5"
    },
    "ModelVarianceExplained": 0.0247987314,
    "MotionNoise": true,
    "TotalVarianceExplained": 0.023447601
  },
  "aroma_motion_13": {
    "CSFFraction": 0.03,
    "EdgeFraction": 0.45,
    "HighFrequencyContent": 0.57,
    "MaximumRpCorrelation": 0.76,
    "Method": {
      "Name": "ICA-AROMA",
      "Version": "0.4.5"
    },
    "ModelVarianceExplained": 0.023316345,
    "MotionNoise": true,
    "TotalVarianceExplained": 0.0220459807
  },
  "aroma_motion_14": {
    "CSFFraction": 0.04,
    "EdgeFraction": 0.37,
    "HighFrequencyContent": 0.7,
    "MaximumRpCorrelation": 0.92,
    "Method": {
      "Name": "ICA-AROMA",
      "Version": "0.4.5"
    },
    "ModelVarianceExplained": 0.0231834688,
    "MotionNoise": true,
    "TotalVarianceExplained": 0.0219203441
  },
  "aroma_motion_15": {
    "CSFFraction": 0.03,
    "EdgeFraction": 0.56,
    "HighFrequencyContent": 0.42,
    "MaximumRpCorrelation": 0.65,
    "Method": {
      "Name": "ICA-AROMA",
      "Version": "0.4.5"
    },
    "ModelVarianceExplained": 0.0231229034,
    "MotionNoise": true,
    "TotalVarianceExplained": 0.0218630786
  },
  "aroma_motion_16": {
    "CSFFraction": 0.01,
    "EdgeFraction": 0.43,
    "HighFrequencyContent": 0.5,
    "MaximumRpCorrelation": 0.56,
    "Method": {
      "Name": "ICA-AROMA",
      "Version": "0.4.5"
    },
    "ModelVarianceExplained": 0.0228454945,
    "MotionNoise": true,
    "TotalVarianceExplained": 0.021600784
  },
  "aroma_motion_17": {
    "CSFFraction": 0.05,
    "EdgeFraction": 0.53,
    "HighFrequencyContent": 0.23,
    "MaximumRpCorrelation": 0.74,
    "Method": {
      "Name": "ICA-AROMA",
      "Version": "0.4.5"
    },
    "ModelVarianceExplained": 0.0226426618,
    "MotionNoise": true,
    "TotalVarianceExplained": 0.0214090024
  },
  "aroma_motion_18": {
    "CSFFraction": 0.27,
    "EdgeFraction": 0.69,
    "HighFrequencyContent": 0.8,
    "MaximumRpCorrelation": 0.71,
    "Method": {
      "Name": "ICA-AROMA",
      "Version": "0.4.5"
    },
    "ModelVarianceExplained": 0.0223839342,
    "MotionNoise": true,
    "TotalVarianceExplained": 0.0211643712
  },
  "aroma_motion_19": {
    "CSFFraction": 0.0,
    "EdgeFraction": 0.32,
    "HighFrequencyContent": 0.33,
    "MaximumRpCorrelation": 0.78,
    "Method": {
      "Name": "ICA-AROMA",
      "Version": "0.4.5"
    },
    "ModelVarianceExplained": 0.0222785905,
    "MotionNoise": false,
    "TotalVarianceExplained": 0.0210647671
  },
  "aroma_motion_2": {
    "CSFFraction": 0.01,
    "EdgeFraction": 0.74,
    "HighFrequencyContent": 0.06,
    "MaximumRpCorrelation": 0.94,
    "Method": {
      "Name": "ICA-AROMA",
      "Version": "0.4.5"
    },
    "ModelVarianceExplained": 0.0507780537,
    "MotionNoise": true,
    "TotalVarianceExplained": 0.0480114698
  },
  "aroma_motion_20": {
    "CSFFraction": 0.02,
    "EdgeFraction": 0.63,
    "HighFrequencyContent": 0.35,
    "MaximumRpCorrelation": 0.5,
    "Method": {
      "Name": "ICA-AROMA",
      "Version": "0.4.5"
    },
    "ModelVarianceExplained": 0.0217130183,
    "MotionNoise": true,
    "TotalVarianceExplained": 0.0205300095
  },
  "aroma_motion_21": {
    "CSFFraction": 0.0,
    "EdgeFraction": 0.24,
    "HighFrequencyContent": 0.32,
    "MaximumRpCorrelation": 0.84,
    "Method": {
      "Name": "ICA-AROMA",
      "Version": "0.4.5"
    },
    "ModelVarianceExplained": 0.0215856762,
    "MotionNoise": false,
    "TotalVarianceExplained": 0.0204096054
  },
  "aroma_motion_22": {
    "CSFFraction": 0.01,
    "EdgeFraction": 0.53,
    "HighFrequencyContent": 0.22,
    "MaximumRpCorrelation": 0.63,
    "Method": {
      "Name": "ICA-AROMA",
      "Version": "0.4.5"
    },
    "ModelVarianceExplained": 0.0214791322,
    "MotionNoise": false,
    "TotalVarianceExplained": 0.0203088664
  },
  "aroma_motion_23": {
    "CSFFraction": 0.01,
    "EdgeFraction": 0.46,
    "HighFrequencyContent": 0.26,
    "MaximumRpCorrelation": 0.78,
    "Method": {
      "Name": "ICA-AROMA",
      "Version": "0.4.5"
    },
    "ModelVarianceExplained": 0.0204864387,
    "MotionNoise": false,
    "TotalVarianceExplained": 0.0193702586
  },
  "aroma_motion_24": {
    "CSFFraction": 0.05,
    "EdgeFraction": 0.69,
    "HighFrequencyContent": 0.28,
    "MaximumRpCorrelation": 0.57,
    "Method": {
      "Name": "ICA-AROMA",
      "Version": "0.4.5"
    },
    "ModelVarianceExplained": 0.0203024846,
    "MotionNoise": true,
    "TotalVarianceExplained": 0.0191963271
  },
  "aroma_motion_25": {
    "CSFFraction": 0.02,
    "EdgeFraction": 0.22,
    "HighFrequencyContent": 0.32,
    "MaximumRpCorrelation": 0.61,
    "Method": {
      "Name": "ICA-AROMA",
      "Version": "0.4.5"
    },
    "ModelVarianceExplained": 0.0197866305,
    "MotionNoise": false,
    "TotalVarianceExplained": 0.0187085787
  },
  "aroma_motion_26": {
    "CSFFraction": 0.01,
    "EdgeFraction": 0.44,
    "HighFrequencyContent": 0.4,
    "MaximumRpCorrelation": 0.63,
    "Method": {
      "Name": "ICA-AROMA",
      "Version": "0.4.5"
    },
    "ModelVarianceExplained": 0.0195386452,
    "MotionNoise": true,
    "TotalVarianceExplained": 0.0184741046
  },
  "aroma_motion_27": {
    "CSFFraction": 0.0,
    "EdgeFraction": 0.25,
    "HighFrequencyContent": 0.38,
    "MaximumRpCorrelation": 0.79,
    "Method": {
      "Name": "ICA-AROMA",
      "Version": "0.4.5"
    },
    "ModelVarianceExplained": 0.0195140478,
    "MotionNoise": true,
    "TotalVarianceExplained": 0.0184508473
  },
  "aroma_motion_28": {
    "CSFFraction": 0.02,
    "EdgeFraction": 0.59,
    "HighFrequencyContent": 0.56,
    "MaximumRpCorrelation": 0.67,
    "Method": {
      "Name": "ICA-AROMA",
      "Version": "0.4.5"
    },
    "ModelVarianceExplained": 0.0194561963,
    "MotionNoise": true,
    "TotalVarianceExplained": 0.0183961478
  },
  "aroma_motion_29": {
    "CSFFraction": 0.01,
    "EdgeFraction": 0.18,
    "HighFrequencyContent": 0.38,
    "MaximumRpCorrelation": 0.6,
    "Method": {
      "Name": "ICA-AROMA",
      "Version": "0.4.5"
    },
    "ModelVarianceExplained": 0.0194061227,
    "MotionNoise": true,
    "TotalVarianceExplained": 0.0183488024
  },
  "aroma_motion_3": {
    "CSFFraction": 0.01,
    "EdgeFraction": 0.65,
    "HighFrequencyContent": 0.12,
    "MaximumRpCorrelation": 0.86,
    "Method": {
      "Name": "ICA-AROMA",
      "Version": "0.4.5"
    },
    "ModelVarianceExplained": 0.0378274583,
    "MotionNoise": true,
    "TotalVarianceExplained": 0.0357664727
  },
  "aroma_motion_30": {
    "CSFFraction": 0.01,
    "EdgeFraction": 0.38,
    "HighFrequencyContent": 0.38,
    "MaximumRpCorrelation": 0.89,
    "Method": {
      "Name": "ICA-AROMA",
      "Version": "0.4.5"
    },
    "ModelVarianceExplained": 0.0193488705,
    "MotionNoise": true,
    "TotalVarianceExplained": 0.0182946695
  },
  "aroma_motion_31": {
    "CSFFraction": 0.27,
    "EdgeFraction": 0.74,
    "HighFrequencyContent": 0.29,
    "MaximumRpCorrelation": 0.54,
    "Method": {
      "Name": "ICA-AROMA",
      "Version": "0.4.5"
    },
    "ModelVarianceExplained": 0.0189947472,
    "MotionNoise": true,
    "TotalVarianceExplained": 0.0179598402
  },
  "aroma_motion_32": {
    "CSFFraction": 0.01,
    "EdgeFraction": 0.41,
    "HighFrequencyContent": 0.26,
    "MaximumRpCorrelation": 0.69,
    "Method": {
      "Name": "ICA-AROMA",
      "Version": "0.4.5"
    },
    "ModelVarianceExplained": 0.0182030888,
    "MotionNoise": false,
    "TotalVarianceExplained": 0.0172113144
  },
  "aroma_motion_33": {
    "CSFFraction": 0.02,
    "EdgeFraction": 0.36,
    "HighFrequencyContent": 0.38,
    "MaximumRpCorrelation": 0.65,
    "Method": {
      "Name": "ICA-AROMA",
      "Version": "0.4.5"
    },
    "ModelVarianceExplained": 0.0178735136,
    "MotionNoise": true,
    "TotalVarianceExplained": 0.0168996958
  },
  "aroma_motion_34": {
    "CSFFraction": 0.11,
    "EdgeFraction": 0.54,
    "HighFrequencyContent": 0.48,
    "MaximumRpCorrelation": 0.72,
    "Method": {
      "Name": "ICA-AROMA",
      "Version": "0.4.5"
    },
    "ModelVarianceExplained": 0.016779868,
    "MotionNoise": true,
    "TotalVarianceExplained": 0.0158656362
  },
  "aroma_motion_35": {
    "CSFFraction": 0.0,
    "EdgeFraction": 0.34,
    "HighFrequencyContent": 0.16,
    "MaximumRpCorrelation": 0.86,
    "Method": {
      "Name": "ICA-AROMA",
      "Version": "0.4.5"
    },
    "ModelVarianceExplained": 0.0167570554,
    "MotionNoise": false,
    "TotalVarianceExplained": 0.0158440664
  },
  "aroma_motion_36": {
    "CSFFraction": 0.01,
    "EdgeFraction": 0.47,
    "HighFrequencyContent": 0.39,
    "MaximumRpCorrelation": 0.8,
    "Method": {
      "Name": "ICA-AROMA",
      "Version": "0.4.5"
    },
    "ModelVarianceExplained": 0.0166467247,
    "MotionNoise": true,
    "TotalVarianceExplained": 0.0157397471
  },
  "aroma_motion_37": {
    "CSFFraction": 0.0,
    "EdgeFraction": 0.31,
    "HighFrequencyContent": 0.29,
    "MaximumRpCorrelation": 0.75,
    "Method": {
      "Name": "ICA-AROMA",
      "Version": "0.4.5"
    },
    "ModelVarianceExplained": 0.0153980109,
    "MotionNoise": false,
    "TotalVarianceExplained": 0.014559068
  },
  "aroma_motion_38": {
    "CSFFraction": 0.11,
    "EdgeFraction": 0.53,
    "HighFrequencyContent": 0.55,
    "MaximumRpCorrelation": 0.8,
    "Method": {
      "Name": "ICA-AROMA",
      "Version": "0.4.5"
    },
    "ModelVarianceExplained": 0.0143665059,
    "MotionNoise": true,
    "TotalVarianceExplained": 0.0135837634
  },
  "aroma_motion_39": {
    "CSFFraction": 0.12,
    "EdgeFraction": 0.49,
    "HighFrequencyContent": 0.43,
    "MaximumRpCorrelation": 0.63,
    "Method": {
      "Name": "ICA-AROMA",
      "Version": "0.4.5"
    },
    "ModelVarianceExplained": 0.0139021838,
    "MotionNoise": true,
    "TotalVarianceExplained": 0.0131447393
  },
  "aroma_motion_4": {
    "CSFFraction": 0.05,
    "EdgeFraction": 0.78,
    "HighFrequencyContent": 0.23,
    "MaximumRpCorrelation": 0.96,
    "Method": {
      "Name": "ICA-AROMA",
      "Version": "0.4.5"
    },
    "ModelVarianceExplained": 0.0367061898,
    "MotionNoise": true,
    "TotalVarianceExplained": 0.0347062952
  },
  "aroma_motion_40": {
    "CSFFraction": 0.11,
    "EdgeFraction": 0.6,
    "HighFrequencyContent": 0.53,
    "MaximumRpCorrelation": 0.5,
    "Method": {
      "Name": "ICA-AROMA",
      "Version": "0.4.5"
    },
    "ModelVarianceExplained": 0.0134440011,
    "MotionNoise": true,
    "TotalVarianceExplained": 0.0127115202
  },
  "aroma_motion_5": {
    "CSFFraction": 0.01,
    "EdgeFraction": 0.55,
    "HighFrequencyContent": 0.06,
    "MaximumRpCorrelation": 0.73,
    "Method": {
      "Name": "ICA-AROMA",
      "Version": "0.4.5"
    },
    "ModelVarianceExplained": 0.0341542565,
    "MotionNoise": true,
    "TotalVarianceExplained": 0.0322934011
  },
  "aroma_motion_6": {
    "CSFFraction": 0.0,
    "EdgeFraction": 0.22,
    "HighFrequencyContent": 0.79,
    "MaximumRpCorrelation": 0.88,
    "Method": {
      "Name": "ICA-AROMA",
      "Version": "0.4.5"
    },
    "ModelVarianceExplained": 0.0331350689,
    "MotionNoise": true,
    "TotalVarianceExplained": 0.0313297427
  },
  "aroma_motion_7": {
    "CSFFraction": 0.01,
    "EdgeFraction": 0.64,
    "HighFrequencyContent": 0.4,
    "MaximumRpCorrelation": 0.66,
    "Method": {
      "Name": "ICA-AROMA",
      "Version": "0.4.5"
    },
    "ModelVarianceExplained": 0.0281131656,
    "MotionNoise": true,
    "TotalVarianceExplained": 0.026581452
  },
  "aroma_motion_8": {
    "CSFFraction": 0.01,
    "EdgeFraction": 0.49,
    "HighFrequencyContent": 0.19,
    "MaximumRpCorrelation": 0.74,
    "Method": {
      "Name": "ICA-AROMA",
      "Version": "0.4.5"
    },
    "ModelVarianceExplained": 0.0272520103,
    "MotionNoise": false,
    "TotalVarianceExplained": 0.0257672158
  },
  "aroma_motion_9": {
    "CSFFraction": 0.0,
    "EdgeFraction": 0.43,
    "HighFrequencyContent": 0.18,
    "MaximumRpCorrelation": 0.67,
    "Method": {
      "Name": "ICA-AROMA",
      "Version": "0.4.5"
    },
    "ModelVarianceExplained": 0.0257564604,
    "MotionNoise": false,
    "TotalVarianceExplained": 0.0243531492
  },
  "c_comp_cor_00": {
    "CumulativeVarianceExplained": 0.1432431433,
    "Mask": "CSF",
    "Method": "aCompCor",
    "Retained": true,
    "SingularValue": 101.5321589196,
    "VarianceExplained": 0.1432431433
  },
  "c_comp_cor_01": {
    "CumulativeVarianceExplained": 0.2327337591,
    "Mask": "CSF",
    "Method": "aCompCor",
    "Retained": true,
    "SingularValue": 80.2519230224,
    "VarianceExplained": 0.0894906158
  },
  "c_comp_cor_02": {
    "CumulativeVarianceExplained": 0.3117826997,
    "Mask": "CSF",
    "Method": "aCompCor",
    "Retained": true,
    "SingularValue": 75.4248971227,
    "VarianceExplained": 0.0790489406
  },
  "c_comp_cor_03": {
    "CumulativeVarianceExplained": 0.3758422368,
    "Mask": "CSF",
    "Method": "aCompCor",
    "Retained": true,
    "SingularValue": 67.8982526126,
    "VarianceExplained": 0.0640595371
  },
  "c_comp_cor_04": {
    "CumulativeVarianceExplained": 0.4340492731,
    "Mask": "CSF",
    "Method": "aCompCor",
    "Retained": true,
    "SingularValue": 64.7223746227,
    "VarianceExplained": 0.0582070362
  },
  "c_comp_cor_05": {
    "CumulativeVarianceExplained": 0.478138123,
    "Mask": "CSF",
    "Method": "aCompCor",
    "Retained": true,
    "SingularValue": 56.3288759367,
    "VarianceExplained": 0.0440888499
  },
  "c_comp_cor_06": {
    "CumulativeVarianceExplained": 0.5150304329,
    "Mask": "CSF",
    "Method": "aCompCor",
    "Retained": true,
    "SingularValue": 51.5269722044,
    "VarianceExplained": 0.0368923099
  },
  "csf": {
    "Method": "Mean"
  },
  "csf_wm": {
    "Method": "Mean"
  },
  "global_signal": {
    "Method": "Mean"
  },
  "t_comp_cor_00": {
    "CumulativeVarianceExplained": 0.4620886355,
    "Method": "tCompCor",
    "Retained": true,
    "SingularValue": 368.1956354459,
    "VarianceExplained": 0.4620886355
  },
  "t_comp_cor_01": {
    "CumulativeVarianceExplained": 0.5268564082,
    "Method": "tCompCor",
    "Retained": true,
    "SingularValue": 137.8464142563,
    "VarianceExplained": 0.0647677727
  },
  "tcompcor": {
    "Method": "Mean"
  },
  "w_comp_cor_00": {
    "CumulativeVarianceExplained": 0.0957500333,
    "Mask": "WM",
    "Method": "aCompCor",
    "Retained": true,
    "SingularValue": 221.2124985418,
    "VarianceExplained": 0.0957500333
  },
  "w_comp_cor_01": {
    "CumulativeVarianceExplained": 0.135045057,
    "Mask": "WM",
    "Method": "aCompCor",
    "Retained": true,
    "SingularValue": 141.7127650674,
    "VarianceExplained": 0.0392950237
  },
  "w_comp_cor_02": {
    "CumulativeVarianceExplained": 0.1636980734,
    "Mask": "WM",
    "Method": "aCompCor",
    "Retained": true,
    "SingularValue": 121.0111443757,
    "VarianceExplained": 0.0286530163
  },
  "w_comp_cor_03": {
    "CumulativeVarianceExplained": 0.1911166215,
    "Mask": "WM",
    "Method": "aCompCor",
    "Retained": true,
    "SingularValue": 118.3756622475,
    "VarianceExplained": 0.0274185482
  },
  "w_comp_cor_04": {
    "CumulativeVarianceExplained": 0.2128699244,
    "Mask": "WM",
    "Method": "aCompCor",
    "Retained": true,
    "SingularValue": 105.4393687962,
    "VarianceExplained": 0.0217533029
  },
  "w_comp_cor_05": {
    "CumulativeVarianceExplained": 0.2311185263,
    "Mask": "WM",
    "Method": "aCompCor",
    "Retained": true,
    "SingularValue": 96.5728377283,
    "VarianceExplained": 0.0182486019
  },
  "w_comp_cor_06": {
    "CumulativeVarianceExplained": 0.24515784,
    "Mask": "WM",
    "Method": "aCompCor",
    "Retained": true,
    "SingularValue": 84.705797048,
    "VarianceExplained": 0.0140393137
  },
  "w_comp_cor_07": {
    "CumulativeVarianceExplained": 0.2578555743,
    "Mask": "WM",
    "Method": "aCompCor",
    "Retained": true,
    "SingularValue": 80.5570049463,
    "VarianceExplained": 0.0126977343
  },
  "w_comp_cor_08": {
    "CumulativeVarianceExplained": 0.2697156786,
    "Mask": "WM",
    "Method": "aCompCor",
    "Retained": true,
    "SingularValue": 77.8546306934,
    "VarianceExplained": 0.0118601043
  },
  "w_comp_cor_09": {
    "CumulativeVarianceExplained": 0.2803550825,
    "Mask": "WM",
    "Method": "aCompCor",
    "Retained": true,
    "SingularValue": 73.7392712506,
    "VarianceExplained": 0.0106394038
  },
  "w_comp_cor_10": {
    "CumulativeVarianceExplained": 0.2907801397,
    "Mask": "WM",
    "Method": "aCompCor",
    "Retained": true,
    "SingularValue": 72.9926982836,
    "VarianceExplained": 0.0104250572
  },
  "w_comp_cor_11": {
    "CumulativeVarianceExplained": 0.3003256511,
    "Mask": "WM",
    "Method": "aCompCor",
    "Retained": true,
    "SingularValue": 69.8457192242,
    "VarianceExplained": 0.0095455114
  },
  "w_comp_cor_12": {
    "CumulativeVarianceExplained": 0.3097227317,
    "Mask": "WM",
    "Method": "aCompCor",
    "Retained": true,
    "SingularValue": 69.3005482142,
    "VarianceExplained": 0.0093970806
  },
  "w_comp_cor_13": {
    "CumulativeVarianceExplained": 0.3187893215,
    "Mask": "WM",
    "Method": "aCompCor",
    "Retained": true,
    "SingularValue": 68.0710076537,
    "VarianceExplained": 0.0090665899
  },
  "w_comp_cor_14": {
    "CumulativeVarianceExplained": 0.3275494361,
    "Mask": "WM",
    "Method": "aCompCor",
    "Retained": true,
    "SingularValue": 66.9106252303,
    "VarianceExplained": 0.0087601146
  },
  "w_comp_cor_15": {
    "CumulativeVarianceExplained": 0.3359796457,
    "Mask": "WM",
    "Method": "aCompCor",
    "Retained": true,
    "SingularValue": 65.6386105546,
    "VarianceExplained": 0.0084302096
  },
  "w_comp_cor_16": {
    "CumulativeVarianceExplained": 0.3441294614,
    "Mask": "WM",
    "Method": "aCompCor",
    "Retained": true,
    "SingularValue": 64.5377900208,
    "VarianceExplained": 0.0081498158
  },
  "w_comp_cor_17": {
    "CumulativeVarianceExplained": 0.3521653526,
    "Mask": "WM",
    "Method": "aCompCor",
    "Retained": true,
    "SingularValue": 64.0851221666,
    "VarianceExplained": 0.0080358911
  },
  "w_comp_cor_18": {
    "CumulativeVarianceExplained": 0.3600786025,
    "Mask": "WM",
    "Method": "aCompCor",
    "Retained": true,
    "SingularValue": 63.594218533,
    "VarianceExplained": 0.0079132499
  },
  "w_comp_cor_19": {
    "CumulativeVarianceExplained": 0.3678927277,
    "Mask": "WM",
    "Method": "aCompCor",
    "Retained": true,
    "SingularValue": 63.1946593007,
    "VarianceExplained": 0.0078141252
  },
  "w_comp_cor_20": {
    "CumulativeVarianceExplained": 0.375586355,
    "Mask": "WM",
    "Method": "aCompCor",
    "Retained": true,
    "SingularValue": 62.7055191208,
    "VarianceExplained": 0.0076936273
  },
  "w_comp_cor_21": {
    "CumulativeVarianceExplained": 0.3831746117,
    "Mask": "WM",
    "Method": "aCompCor",
    "Retained": true,
    "SingularValue": 62.2746364463,
    "VarianceExplained": 0.0075882567
  },
  "w_comp_cor_22": {
    "CumulativeVarianceExplained": 0.3905909791,
    "Mask": "WM",
    "Method": "aCompCor",
    "Retained": true,
    "SingularValue": 61.5652733982,
    "VarianceExplained": 0.0074163674
  },
  "w_comp_cor_23": {
    "CumulativeVarianceExplained": 0.3979428097,
    "Mask": "WM",
    "Method": "aCompCor",
    "Retained": true,
    "SingularValue": 61.2968191098,
    "VarianceExplained": 0.0073518305
  },
  "w_comp_cor_24": {
    "CumulativeVarianceExplained": 0.4052698719,
    "Mask": "WM",
    "Method": "aCompCor",
    "Retained": true,
    "SingularValue": 61.1934774253,
    "VarianceExplained": 0.0073270622
  },
  "w_comp_cor_25": {
    "CumulativeVarianceExplained": 0.4125031907,
    "Mask": "WM",
    "Method": "aCompCor",
    "Retained": true,
    "SingularValue": 60.8007585473,
    "VarianceExplained": 0.0072333188
  },
  "w_comp_cor_26": {
    "CumulativeVarianceExplained": 0.4196877954,
    "Mask": "WM",
    "Method": "aCompCor",
    "Retained": true,
    "SingularValue": 60.5956761391,
    "VarianceExplained": 0.0071846048
  },
  "w_comp_cor_27": {
    "CumulativeVarianceExplained": 0.4267992537,
    "Mask": "WM",
    "Method": "aCompCor",
    "Retained": true,
    "SingularValue": 60.2864245237,
    "VarianceExplained": 0.0071114583
  },
  "w_comp_cor_28": {
    "CumulativeVarianceExplained": 0.4338077375,
    "Mask": "WM",
    "Method": "aCompCor",
    "Retained": true,
    "SingularValue": 59.8483565337,
    "VarianceExplained": 0.0070084837
  },
  "w_comp_cor_29": {
    "CumulativeVarianceExplained": 0.4407537807,
    "Mask": "WM",
    "Method": "aCompCor",
    "Retained": true,
    "SingularValue": 59.5811573251,
    "VarianceExplained": 0.0069460432
  },
  "w_comp_cor_30": {
    "CumulativeVarianceExplained": 0.4476467252,
    "Mask": "WM",
    "Method": "aCompCor",
    "Retained": true,
    "SingularValue": 59.3529876561,
    "VarianceExplained": 0.0068929445
  },
  "w_comp_cor_31": {
    "CumulativeVarianceExplained": 0.4545283249,
    "Mask": "WM",
    "Method": "aCompCor",
    "Retained": true,
    "SingularValue": 59.3041242802,
    "VarianceExplained": 0.0068815997
  },
  "w_comp_cor_32": {
    "CumulativeVarianceExplained": 0.4613547457,
    "Mask": "WM",
    "Method": "aCompCor",
    "Retained": true,
    "SingularValue": 59.0658861038,
    "VarianceExplained": 0.0068264208
  },
  "w_comp_cor_33": {
    "CumulativeVarianceExplained": 0.4681538258,
    "Mask": "WM",
    "Method": "aCompCor",
    "Retained": true,
    "SingularValue": 58.9474839694,
    "VarianceExplained": 0.0067990801
  },
  "w_comp_cor_34": {
    "CumulativeVarianceExplained": 0.4749178489,
    "Mask": "WM",
    "Method": "aCompCor",
    "Retained": true,
    "SingularValue": 58.7953168633,
    "VarianceExplained": 0.0067640231
  },
  "w_comp_cor_35": {
    "CumulativeVarianceExplained": 0.4815791534,
    "Mask": "WM",
    "Method": "aCompCor",
    "Retained": true,
    "SingularValue": 58.3471752695,
    "VarianceExplained": 0.0066613044
  },
  "w_comp_cor_36": {
    "CumulativeVarianceExplained": 0.4882175113,
    "Mask": "WM",
    "Method": "aCompCor",
    "Retained": true,
    "SingularValue": 58.2465931375,
    "VarianceExplained": 0.006638358
  },
  "w_comp_cor_37": {
    "CumulativeVarianceExplained": 0.49481667,
    "Mask": "WM",
    "Method": "aCompCor",
    "Retained": true,
    "SingularValue": 58.0743663954,
    "VarianceExplained": 0.0065991587
  },
  "w_comp_cor_38": {
    "CumulativeVarianceExplained": 0.5013368812,
    "Mask": "WM",
    "Method": "aCompCor",
    "Retained": true,
    "SingularValue": 57.7259415882,
    "VarianceExplained": 0.0065202112
  },
  "white_matter": {
    "Method": "Mean"
  }
}